{
  "name": "devnet",
  "messagePrefix": "KNOW message:\n",
  "bip32": {
    "public": 46090600,
    "private": 46089520
  },
  "pubKeyHash": 45,
  "nethash": "360f42a0fedd0865b46fda3f853f2273431c041bbc2eaf4fe8be8c2ab174bf02",
  "wif": 170,
  "client": {
    "token": "KNOW",
    "symbol": "KN",
    "explorer": "https://dev.explorer.knownetwork.io"
  },
  "constants": [{
    "height": 1,
    "reward": 2500000000,
    "activeDelegates": 37,
    "blocktime": 5,
    "block": {
      "version": 0,
      "maxTransactions": 50,
      "maxPayload": 2097152
    },
    "epoch": "2018-03-21T13:00:00.000Z",
    "fees": {
      "dynamic" : false,
      "transfer": 10000000,
      "secondSignature": 1000000000,
      "delegateRegistration": 10000000000,
      "vote": 1000000000,
      "multiSignature": 1000000000,
      "ipfs": 0,
      "timelockTransfer": 0,
      "multiPayment": 0,
      "delegateResignation": 0
    },
    "dynamicOffsets": {
      "transfer": 100,
      "secondSignature": 250,
      "delegateRegistration": 500,
      "vote": 100,
      "multiSignature": 500,
      "ipfs": 250,
      "timelockTransfer": 500,
      "multiPayment": 500,
      "delegateResignation": 500
    }
  }, {
    "height": 75600,
    "reward": 2500000000
  }],
  "exceptions": {
  }
}
